roxCrypter/__init__.py
roxCrypter-1.0.1.dist-info/LICENSE.md
roxCrypter-1.0.1.dist-info/METADATA
roxCrypter-1.0.1.dist-info/WHEEL
roxCrypter-1.0.1.dist-info/top_level.txt
roxCrypter-1.0.1.dist-info/RECORD
