Metadata-Version: 2.1
Name: roxCrypter
Version: 1.0.1
Summary: A custom encryption package for blank text & passwords
Home-page: https://github.com/sametkarapinar/roxCrypter
Author: Samet Karapınar
Author-email: skrpnr4@gmail.com
Project-URL: Source, https://github.com/sametkarapinar/roxCrypter
Requires-Python: >=3.6
License-File: LICENSE.md
